refacto/__init__.py
refacto/exceptions.py
refacto/lsp_utilities.py
refacto/main.py
refacto/refactoring_service.py
refacto/server.py
refacto/version.py
refacto/core/__init__.py
refacto/core/refactoring.py
refacto/core/refactoring_transformer.py
refacto/core/refactoring_visitor.py
refacto/refactorings/__init__.py
refacto/refactorings/extract_variable/__init__.py
refacto/refactorings/extract_variable/extraction_strategies.py
refacto/refactorings/extract_variable/refactor.py
refacto/refactorings/extract_variable/transformer.py
refacto/refactorings/extract_variable/visitor.py
refacto/refactorings/inline_variable/__init__.py
refacto/refactorings/inline_variable/refactor.py
refacto/refactorings/inline_variable/transformer.py
refacto/refactorings/inline_variable/visitor.py
py_refacto-0.0.12.dist-info/LICENSE
py_refacto-0.0.12.dist-info/METADATA
py_refacto-0.0.12.dist-info/WHEEL
py_refacto-0.0.12.dist-info/entry_points.txt
py_refacto-0.0.12.dist-info/top_level.txt
py_refacto-0.0.12.dist-info/RECORD
