Metadata-Version: 2.1
Name: py-refacto
Version: 0.0.12
Summary: Refacto
Home-page: https://github.com/nymann/refacto
Maintainer: Kristian Nymann Jakobsen
Maintainer-email: kristian@nymann.dev
Requires-Python: >=3.9
License-File: LICENSE
Requires-Dist: pygls
Requires-Dist: libcst
Requires-Dist: typer
Provides-Extra: all
Requires-Dist: add-trailing-comma ; extra == 'all'
Requires-Dist: black ; extra == 'all'
Requires-Dist: isort ; extra == 'all'
Requires-Dist: mypy ; extra == 'all'
Requires-Dist: nitpick ; extra == 'all'
Requires-Dist: wemake-python-styleguide ; extra == 'all'
Requires-Dist: devtools ; extra == 'all'
Requires-Dist: pytest ; extra == 'all'
Requires-Dist: pytest-cov ; extra == 'all'
Requires-Dist: pytest-mock ; extra == 'all'
Provides-Extra: dev
Requires-Dist: add-trailing-comma ; extra == 'dev'
Requires-Dist: black ; extra == 'dev'
Requires-Dist: isort ; extra == 'dev'
Requires-Dist: mypy ; extra == 'dev'
Requires-Dist: nitpick ; extra == 'dev'
Requires-Dist: wemake-python-styleguide ; extra == 'dev'
Provides-Extra: tests
Requires-Dist: devtools ; extra == 'tests'
Requires-Dist: pytest ; extra == 'tests'
Requires-Dist: pytest-cov ; extra == 'tests'
Requires-Dist: pytest-mock ; extra == 'tests'
